{"family":"[]","activities":["easter.buzzer.iconosys.ChristmasTimer","easter.buzzer.iconosys.OtherApps","easter.buzzer.iconosys.ContactsList"],"services":["easter.buzzer.iconosys.MessageService"],"receivers":[],"iccg":[{"val0":"easter.buzzer.iconosys.ChristmasTimer","val1":"easter.buzzer.iconosys.OtherApps"},{"val0":"easter.buzzer.iconosys.ChristmasTimer","val1":"easter.buzzer.iconosys.ContactsList"}],"intentFilters":[],"dangerAPIs":[{"val0":"easter.buzzer.iconosys.ChristmasTimer","val1":"\u003candroid.telephony.SmsManager: void sendTextMessage(java.lang.String,java.lang.String,java.lang.String,android.app.PendingIntent,android.app.PendingIntent)\u003e"}],"taintFlows":[{"val0":"easter.buzzer.iconosys.ChristmasTimer","val1":"$getDeviceId","val2":"easter.buzzer.iconosys.ChristmasTimer","val3":"!INTERNET"},{"val0":"easter.buzzer.iconosys.ChristmasTimer","val1":"$getLine1Number","val2":"easter.buzzer.iconosys.ChristmasTimer","val3":"!sendTextMessage"},{"val0":"easter.buzzer.iconosys.ChristmasTimer","val1":"$getLine1Number","val2":"easter.buzzer.iconosys.ChristmasTimer","val3":"!INTERNET"},{"val0":"easter.buzzer.iconosys.ChristmasTimer","val1":"$MODEL","val2":"easter.buzzer.iconosys.ChristmasTimer","val3":"!INTERNET"},{"val0":"easter.buzzer.iconosys.ChristmasTimer","val1":"$BRAND","val2":"easter.buzzer.iconosys.ChristmasTimer","val3":"!INTERNET"},{"val0":"easter.buzzer.iconosys.ChristmasTimer","val1":"$PRODUCT","val2":"easter.buzzer.iconosys.ChristmasTimer","val3":"!INTERNET"}],"samples":[]}