{"family":"[]","activities":["jp.lptqsnvvauu.owgfihf.Settings","com.EvamVKm.vEphGedQWhKRkQ","jp.lptqsnvvauu.owgfihf.Game","jp.lptqsnvvauu.owgfihf.Andjong","com.EvamVKm.AkfUcwshMQDdQ","jp.lptqsnvvauu.owgfihf.About"],"services":[],"receivers":[],"iccg":[{"val0":"com.EvamVKm.vEphGedQWhKRkQ","val1":"jp.lptqsnvvauu.owgfihf.Andjong"},{"val0":"com.EvamVKm.vEphGedQWhKRkQ","val1":"com.EvamVKm.AkfUcwshMQDdQ"},{"val0":"jp.lptqsnvvauu.owgfihf.Andjong","val1":"jp.lptqsnvvauu.owgfihf.Settings"},{"val0":"jp.lptqsnvvauu.owgfihf.Andjong","val1":"jp.lptqsnvvauu.owgfihf.Game"},{"val0":"jp.lptqsnvvauu.owgfihf.Andjong","val1":"jp.lptqsnvvauu.owgfihf.About"},{"val0":"com.EvamVKm.AkfUcwshMQDdQ","val1":"jp.lptqsnvvauu.owgfihf.Andjong"},{"val0":"com.EvamVKm.AkfUcwshMQDdQ","val1":"INSTALL_APK"}],"intentFilters":[],"dangerAPIs":[],"taintFlows":[{"val0":"com.EvamVKm.vEphGedQWhKRkQ","val1":"$getDeviceId","val2":"com.EvamVKm.vEphGedQWhKRkQ","val3":"!INTERNET"},{"val0":"com.EvamVKm.vEphGedQWhKRkQ","val1":"$getSimSerialNumber","val2":"com.EvamVKm.vEphGedQWhKRkQ","val3":"!INTERNET"},{"val0":"com.EvamVKm.vEphGedQWhKRkQ","val1":"$getSubscriberId","val2":"com.EvamVKm.vEphGedQWhKRkQ","val3":"!INTERNET"},{"val0":"com.EvamVKm.vEphGedQWhKRkQ","val1":"$getLine1Number","val2":"com.EvamVKm.vEphGedQWhKRkQ","val3":"!INTERNET"}]}