{"family":"[]","activities":["com.waps.OffersWebView","movecont2.musichuangmeixi.MyMain"],"services":[],"receivers":[],"iccg":[{"val0":"movecont2.musichuangmeixi.MyMain","val1":"com.waps.OffersWebView"}],"intentFilters":[],"dangerAPIs":[],"taintFlows":[{"val0":"com.waps.OffersWebView","val1":"$InstalledPackages","val2":"com.waps.OffersWebView","val3":"!WebView"},{"val0":"com.waps.OffersWebView","val1":"$InstalledPackages","val2":"com.waps.OffersWebView","val3":"!INTERNET"},{"val0":"com.waps.OffersWebView","val1":"$getDeviceId","val2":"com.waps.OffersWebView","val3":"!WebView"},{"val0":"com.waps.OffersWebView","val1":"$getDeviceId","val2":"com.waps.OffersWebView","val3":"!INTERNET"},{"val0":"com.waps.OffersWebView","val1":"$getSubscriberId","val2":"com.waps.OffersWebView","val3":"!WebView"},{"val0":"com.waps.OffersWebView","val1":"$getSubscriberId","val2":"com.waps.OffersWebView","val3":"!INTERNET"},{"val0":"com.waps.OffersWebView","val1":"$MODEL","val2":"com.waps.OffersWebView","val3":"!WebView"},{"val0":"com.waps.OffersWebView","val1":"$MODEL","val2":"com.waps.OffersWebView","val3":"!INTERNET"},{"val0":"com.waps.OffersWebView","val1":"$MyTime","val2":"com.waps.OffersWebView","val3":"!WebView"},{"val0":"com.waps.OffersWebView","val1":"$MyTime","val2":"com.waps.OffersWebView","val3":"!INTERNET"},{"val0":"com.waps.OffersWebView","val1":"$InstalledPackages","val2":"movecont2.musichuangmeixi.MyMain","val3":"!INTERNET"},{"val0":"com.waps.OffersWebView","val1":"$getDeviceId","val2":"movecont2.musichuangmeixi.MyMain","val3":"!INTERNET"},{"val0":"com.waps.OffersWebView","val1":"$getSubscriberId","val2":"movecont2.musichuangmeixi.MyMain","val3":"!INTERNET"},{"val0":"com.waps.OffersWebView","val1":"$MODEL","val2":"movecont2.musichuangmeixi.MyMain","val3":"!INTERNET"},{"val0":"com.waps.OffersWebView","val1":"$MyTime","val2":"movecont2.musichuangmeixi.MyMain","val3":"!INTERNET"},{"val0":"movecont2.musichuangmeixi.MyMain","val1":"$InstalledPackages","val2":"com.waps.OffersWebView","val3":"!WebView"},{"val0":"movecont2.musichuangmeixi.MyMain","val1":"$InstalledPackages","val2":"com.waps.OffersWebView","val3":"!INTERNET"},{"val0":"movecont2.musichuangmeixi.MyMain","val1":"$getDeviceId","val2":"com.waps.OffersWebView","val3":"!WebView"},{"val0":"movecont2.musichuangmeixi.MyMain","val1":"$getDeviceId","val2":"com.waps.OffersWebView","val3":"!INTERNET"},{"val0":"movecont2.musichuangmeixi.MyMain","val1":"$getSubscriberId","val2":"com.waps.OffersWebView","val3":"!WebView"},{"val0":"movecont2.musichuangmeixi.MyMain","val1":"$getSubscriberId","val2":"com.waps.OffersWebView","val3":"!INTERNET"},{"val0":"movecont2.musichuangmeixi.MyMain","val1":"$SDK","val2":"com.waps.OffersWebView","val3":"!WebView"},{"val0":"movecont2.musichuangmeixi.MyMain","val1":"$SDK","val2":"com.waps.OffersWebView","val3":"!INTERNET"},{"val0":"movecont2.musichuangmeixi.MyMain","val1":"$MODEL","val2":"com.waps.OffersWebView","val3":"!WebView"},{"val0":"movecont2.musichuangmeixi.MyMain","val1":"$MODEL","val2":"com.waps.OffersWebView","val3":"!INTERNET"},{"val0":"movecont2.musichuangmeixi.MyMain","val1":"$ExternalStorage","val2":"com.waps.OffersWebView","val3":"!WebView"},{"val0":"movecont2.musichuangmeixi.MyMain","val1":"$ExternalStorage","val2":"com.waps.OffersWebView","val3":"!INTERNET"},{"val0":"movecont2.musichuangmeixi.MyMain","val1":"$MyTime","val2":"com.waps.OffersWebView","val3":"!WebView"},{"val0":"movecont2.musichuangmeixi.MyMain","val1":"$MyTime","val2":"com.waps.OffersWebView","val3":"!INTERNET"},{"val0":"movecont2.musichuangmeixi.MyMain","val1":"$File","val2":"com.waps.OffersWebView","val3":"!WebView"},{"val0":"movecont2.musichuangmeixi.MyMain","val1":"$File","val2":"com.waps.OffersWebView","val3":"!INTERNET"},{"val0":"movecont2.musichuangmeixi.MyMain","val1":"$InstalledPackages","val2":"movecont2.musichuangmeixi.MyMain","val3":"!INTERNET"},{"val0":"movecont2.musichuangmeixi.MyMain","val1":"$getDeviceId","val2":"movecont2.musichuangmeixi.MyMain","val3":"!INTERNET"},{"val0":"movecont2.musichuangmeixi.MyMain","val1":"$getSubscriberId","val2":"movecont2.musichuangmeixi.MyMain","val3":"!INTERNET"},{"val0":"movecont2.musichuangmeixi.MyMain","val1":"$SDK","val2":"movecont2.musichuangmeixi.MyMain","val3":"!INTERNET"},{"val0":"movecont2.musichuangmeixi.MyMain","val1":"$MODEL","val2":"movecont2.musichuangmeixi.MyMain","val3":"!INTERNET"},{"val0":"movecont2.musichuangmeixi.MyMain","val1":"$ExternalStorage","val2":"movecont2.musichuangmeixi.MyMain","val3":"!INTERNET"},{"val0":"movecont2.musichuangmeixi.MyMain","val1":"$MyTime","val2":"movecont2.musichuangmeixi.MyMain","val3":"!INTERNET"},{"val0":"movecont2.musichuangmeixi.MyMain","val1":"$File","val2":"movecont2.musichuangmeixi.MyMain","val3":"!INTERNET"}],"samples":[]}