{"family":"[]","activities":["com.StatesAndCities.PreferenceMemoryTrainerActivity","com.StatesAndCities.FirstSide","com.google.ads.AdActivity"],"services":[],"receivers":[],"iccg":[{"val0":"com.StatesAndCities.FirstSide","val1":"com.StatesAndCities.PreferenceMemoryTrainerActivity"},{"val0":"com.StatesAndCities.FirstSide","val1":"com.StatesAndCities.FirstSide"},{"val0":"com.StatesAndCities.FirstSide","val1":"com.google.ads.AdActivity"}],"intentFilters":[],"dangerAPIs":[],"taintFlows":[],"samples":[]}