{"family":"[]","activities":["com.whawhawhat.jigsawjessicaalba.Jigsaw","com.google.ads.AdActivity","com.whawhawhat.jigsawjessicaalba.Other","com.whawhawhat.jigsawjessicaalba.Intro"],"services":[],"receivers":[],"iccg":[{"val0":"com.whawhawhat.jigsawjessicaalba.Other","val1":"com.whawhawhat.jigsawjessicaalba.Jigsaw"},{"val0":"com.whawhawhat.jigsawjessicaalba.Other","val1":"com.google.ads.AdActivity"},{"val0":"com.whawhawhat.jigsawjessicaalba.Other","val1":"com.whawhawhat.jigsawjessicaalba.Other"},{"val0":"com.whawhawhat.jigsawjessicaalba.Other","val1":"com.whawhawhat.jigsawjessicaalba.Intro"},{"val0":"com.whawhawhat.jigsawjessicaalba.Intro","val1":"com.whawhawhat.jigsawjessicaalba.Jigsaw"},{"val0":"com.whawhawhat.jigsawjessicaalba.Intro","val1":"com.google.ads.AdActivity"},{"val0":"com.whawhawhat.jigsawjessicaalba.Intro","val1":"com.whawhawhat.jigsawjessicaalba.Other"},{"val0":"com.whawhawhat.jigsawjessicaalba.Intro","val1":"com.whawhawhat.jigsawjessicaalba.Intro"}],"intentFilters":[],"dangerAPIs":[],"taintFlows":[],"samples":[]}