{"family":"[]","activities":["net.webmise.textspeaker.TextSpeakerSplashActivity","net.webmise.textspeaker.TextSpeakerForShareActivity","net.webmise.textspeaker.TextSpeakerActivity","net.webmise.textspeaker.TextSpeakerInfoActivity","com.google.ads.AdActivity","net.webmise.textspeaker.dialog.TextSpeakerPitchRateDialogActivity","net.webmise.textspeaker.dialog.TextSpeakerRegistDialogActivity","net.webmise.textspeaker.dialog.TextSpeakerItemMenuDialogActivity","net.webmise.textspeaker.dialog.TextSpeakerSettingDialogActivity"],"services":["net.webmise.textspeaker.TextSpeakerAlarmService"],"receivers":["net.webmise.textspeaker.TextSpeakerStartupReceiver","net.webmise.textspeaker.TextSpeakerSetAlarmReceiver","net.webmise.textspeaker.TextSpeakerAlarmReceiver"],"iccg":[{"val0":"net.webmise.textspeaker.TextSpeakerSplashActivity","val1":"net.webmise.textspeaker.TextSpeakerSplashActivity"},{"val0":"net.webmise.textspeaker.TextSpeakerSplashActivity","val1":"net.webmise.textspeaker.TextSpeakerForShareActivity"},{"val0":"net.webmise.textspeaker.TextSpeakerSplashActivity","val1":"net.webmise.textspeaker.TextSpeakerActivity"},{"val0":"net.webmise.textspeaker.TextSpeakerSplashActivity","val1":"net.webmise.textspeaker.TextSpeakerInfoActivity"},{"val0":"net.webmise.textspeaker.TextSpeakerSplashActivity","val1":"com.google.ads.AdActivity"},{"val0":"net.webmise.textspeaker.TextSpeakerSplashActivity","val1":"net.webmise.textspeaker.dialog.TextSpeakerPitchRateDialogActivity"},{"val0":"net.webmise.textspeaker.TextSpeakerSplashActivity","val1":"net.webmise.textspeaker.TextSpeakerStartupReceiver"},{"val0":"net.webmise.textspeaker.TextSpeakerSplashActivity","val1":"net.webmise.textspeaker.dialog.TextSpeakerRegistDialogActivity"},{"val0":"net.webmise.textspeaker.TextSpeakerActivity","val1":"net.webmise.textspeaker.TextSpeakerSplashActivity"},{"val0":"net.webmise.textspeaker.TextSpeakerActivity","val1":"net.webmise.textspeaker.TextSpeakerForShareActivity"},{"val0":"net.webmise.textspeaker.TextSpeakerActivity","val1":"net.webmise.textspeaker.TextSpeakerActivity"},{"val0":"net.webmise.textspeaker.TextSpeakerActivity","val1":"net.webmise.textspeaker.TextSpeakerInfoActivity"},{"val0":"net.webmise.textspeaker.TextSpeakerActivity","val1":"com.google.ads.AdActivity"},{"val0":"net.webmise.textspeaker.TextSpeakerActivity","val1":"net.webmise.textspeaker.dialog.TextSpeakerPitchRateDialogActivity"},{"val0":"net.webmise.textspeaker.TextSpeakerActivity","val1":"net.webmise.textspeaker.TextSpeakerStartupReceiver"},{"val0":"net.webmise.textspeaker.TextSpeakerActivity","val1":"net.webmise.textspeaker.dialog.TextSpeakerRegistDialogActivity"},{"val0":"net.webmise.textspeaker.TextSpeakerSplashActivity","val1":"net.webmise.textspeaker.TextSpeakerAlarmService"},{"val0":"net.webmise.textspeaker.TextSpeakerSplashActivity","val1":"net.webmise.textspeaker.TextSpeakerSetAlarmReceiver"},{"val0":"net.webmise.textspeaker.TextSpeakerSplashActivity","val1":"net.webmise.textspeaker.TextSpeakerAlarmReceiver"},{"val0":"net.webmise.textspeaker.TextSpeakerSplashActivity","val1":"net.webmise.textspeaker.dialog.TextSpeakerItemMenuDialogActivity"},{"val0":"net.webmise.textspeaker.TextSpeakerActivity","val1":"net.webmise.textspeaker.TextSpeakerAlarmService"},{"val0":"net.webmise.textspeaker.TextSpeakerActivity","val1":"net.webmise.textspeaker.TextSpeakerSetAlarmReceiver"},{"val0":"net.webmise.textspeaker.TextSpeakerActivity","val1":"net.webmise.textspeaker.TextSpeakerAlarmReceiver"},{"val0":"net.webmise.textspeaker.TextSpeakerActivity","val1":"net.webmise.textspeaker.dialog.TextSpeakerItemMenuDialogActivity"},{"val0":"net.webmise.textspeaker.TextSpeakerSplashActivity","val1":"net.webmise.textspeaker.dialog.TextSpeakerSettingDialogActivity"},{"val0":"net.webmise.textspeaker.TextSpeakerActivity","val1":"net.webmise.textspeaker.dialog.TextSpeakerSettingDialogActivity"},{"val0":"net.webmise.textspeaker.TextSpeakerStartupReceiver","val1":"net.webmise.textspeaker.TextSpeakerSplashActivity"},{"val0":"net.webmise.textspeaker.TextSpeakerStartupReceiver","val1":"net.webmise.textspeaker.TextSpeakerForShareActivity"},{"val0":"net.webmise.textspeaker.TextSpeakerStartupReceiver","val1":"net.webmise.textspeaker.TextSpeakerActivity"},{"val0":"net.webmise.textspeaker.TextSpeakerStartupReceiver","val1":"net.webmise.textspeaker.TextSpeakerInfoActivity"},{"val0":"net.webmise.textspeaker.TextSpeakerStartupReceiver","val1":"com.google.ads.AdActivity"},{"val0":"net.webmise.textspeaker.TextSpeakerStartupReceiver","val1":"net.webmise.textspeaker.dialog.TextSpeakerPitchRateDialogActivity"},{"val0":"net.webmise.textspeaker.TextSpeakerStartupReceiver","val1":"net.webmise.textspeaker.TextSpeakerStartupReceiver"},{"val0":"net.webmise.textspeaker.TextSpeakerStartupReceiver","val1":"net.webmise.textspeaker.dialog.TextSpeakerRegistDialogActivity"},{"val0":"net.webmise.textspeaker.TextSpeakerStartupReceiver","val1":"net.webmise.textspeaker.TextSpeakerAlarmService"},{"val0":"net.webmise.textspeaker.TextSpeakerStartupReceiver","val1":"net.webmise.textspeaker.TextSpeakerSetAlarmReceiver"},{"val0":"net.webmise.textspeaker.TextSpeakerStartupReceiver","val1":"net.webmise.textspeaker.TextSpeakerAlarmReceiver"},{"val0":"net.webmise.textspeaker.TextSpeakerStartupReceiver","val1":"net.webmise.textspeaker.dialog.TextSpeakerItemMenuDialogActivity"},{"val0":"net.webmise.textspeaker.TextSpeakerStartupReceiver","val1":"net.webmise.textspeaker.dialog.TextSpeakerSettingDialogActivity"},{"val0":"net.webmise.textspeaker.TextSpeakerAlarmService","val1":"net.webmise.textspeaker.TextSpeakerSplashActivity"},{"val0":"net.webmise.textspeaker.TextSpeakerAlarmService","val1":"net.webmise.textspeaker.TextSpeakerForShareActivity"},{"val0":"net.webmise.textspeaker.TextSpeakerAlarmService","val1":"net.webmise.textspeaker.TextSpeakerActivity"},{"val0":"net.webmise.textspeaker.TextSpeakerAlarmService","val1":"net.webmise.textspeaker.TextSpeakerInfoActivity"},{"val0":"net.webmise.textspeaker.TextSpeakerAlarmService","val1":"com.google.ads.AdActivity"},{"val0":"net.webmise.textspeaker.TextSpeakerAlarmService","val1":"net.webmise.textspeaker.dialog.TextSpeakerPitchRateDialogActivity"},{"val0":"net.webmise.textspeaker.TextSpeakerAlarmService","val1":"net.webmise.textspeaker.TextSpeakerStartupReceiver"},{"val0":"net.webmise.textspeaker.TextSpeakerAlarmService","val1":"net.webmise.textspeaker.dialog.TextSpeakerRegistDialogActivity"},{"val0":"net.webmise.textspeaker.TextSpeakerSetAlarmReceiver","val1":"net.webmise.textspeaker.TextSpeakerSplashActivity"},{"val0":"net.webmise.textspeaker.TextSpeakerSetAlarmReceiver","val1":"net.webmise.textspeaker.TextSpeakerForShareActivity"},{"val0":"net.webmise.textspeaker.TextSpeakerSetAlarmReceiver","val1":"net.webmise.textspeaker.TextSpeakerActivity"},{"val0":"net.webmise.textspeaker.TextSpeakerSetAlarmReceiver","val1":"net.webmise.textspeaker.TextSpeakerInfoActivity"},{"val0":"net.webmise.textspeaker.TextSpeakerSetAlarmReceiver","val1":"com.google.ads.AdActivity"},{"val0":"net.webmise.textspeaker.TextSpeakerSetAlarmReceiver","val1":"net.webmise.textspeaker.dialog.TextSpeakerPitchRateDialogActivity"},{"val0":"net.webmise.textspeaker.TextSpeakerSetAlarmReceiver","val1":"net.webmise.textspeaker.TextSpeakerStartupReceiver"},{"val0":"net.webmise.textspeaker.TextSpeakerSetAlarmReceiver","val1":"net.webmise.textspeaker.dialog.TextSpeakerRegistDialogActivity"},{"val0":"net.webmise.textspeaker.TextSpeakerAlarmReceiver","val1":"net.webmise.textspeaker.TextSpeakerSplashActivity"},{"val0":"net.webmise.textspeaker.TextSpeakerAlarmReceiver","val1":"net.webmise.textspeaker.TextSpeakerForShareActivity"},{"val0":"net.webmise.textspeaker.TextSpeakerAlarmReceiver","val1":"net.webmise.textspeaker.TextSpeakerActivity"},{"val0":"net.webmise.textspeaker.TextSpeakerAlarmReceiver","val1":"net.webmise.textspeaker.TextSpeakerInfoActivity"},{"val0":"net.webmise.textspeaker.TextSpeakerAlarmReceiver","val1":"com.google.ads.AdActivity"},{"val0":"net.webmise.textspeaker.TextSpeakerAlarmReceiver","val1":"net.webmise.textspeaker.dialog.TextSpeakerPitchRateDialogActivity"},{"val0":"net.webmise.textspeaker.TextSpeakerAlarmReceiver","val1":"net.webmise.textspeaker.TextSpeakerStartupReceiver"},{"val0":"net.webmise.textspeaker.TextSpeakerAlarmReceiver","val1":"net.webmise.textspeaker.dialog.TextSpeakerRegistDialogActivity"},{"val0":"net.webmise.textspeaker.dialog.TextSpeakerItemMenuDialogActivity","val1":"net.webmise.textspeaker.TextSpeakerSplashActivity"},{"val0":"net.webmise.textspeaker.dialog.TextSpeakerItemMenuDialogActivity","val1":"net.webmise.textspeaker.TextSpeakerForShareActivity"},{"val0":"net.webmise.textspeaker.dialog.TextSpeakerItemMenuDialogActivity","val1":"net.webmise.textspeaker.TextSpeakerActivity"},{"val0":"net.webmise.textspeaker.dialog.TextSpeakerItemMenuDialogActivity","val1":"net.webmise.textspeaker.TextSpeakerInfoActivity"},{"val0":"net.webmise.textspeaker.dialog.TextSpeakerItemMenuDialogActivity","val1":"com.google.ads.AdActivity"},{"val0":"net.webmise.textspeaker.dialog.TextSpeakerItemMenuDialogActivity","val1":"net.webmise.textspeaker.dialog.TextSpeakerPitchRateDialogActivity"},{"val0":"net.webmise.textspeaker.dialog.TextSpeakerItemMenuDialogActivity","val1":"net.webmise.textspeaker.TextSpeakerStartupReceiver"},{"val0":"net.webmise.textspeaker.dialog.TextSpeakerItemMenuDialogActivity","val1":"net.webmise.textspeaker.dialog.TextSpeakerRegistDialogActivity"},{"val0":"net.webmise.textspeaker.TextSpeakerAlarmService","val1":"net.webmise.textspeaker.TextSpeakerAlarmService"},{"val0":"net.webmise.textspeaker.TextSpeakerAlarmService","val1":"net.webmise.textspeaker.TextSpeakerSetAlarmReceiver"},{"val0":"net.webmise.textspeaker.TextSpeakerAlarmService","val1":"net.webmise.textspeaker.TextSpeakerAlarmReceiver"},{"val0":"net.webmise.textspeaker.TextSpeakerAlarmService","val1":"net.webmise.textspeaker.dialog.TextSpeakerItemMenuDialogActivity"},{"val0":"net.webmise.textspeaker.TextSpeakerSetAlarmReceiver","val1":"net.webmise.textspeaker.TextSpeakerAlarmService"},{"val0":"net.webmise.textspeaker.TextSpeakerSetAlarmReceiver","val1":"net.webmise.textspeaker.TextSpeakerSetAlarmReceiver"},{"val0":"net.webmise.textspeaker.TextSpeakerSetAlarmReceiver","val1":"net.webmise.textspeaker.TextSpeakerAlarmReceiver"},{"val0":"net.webmise.textspeaker.TextSpeakerSetAlarmReceiver","val1":"net.webmise.textspeaker.dialog.TextSpeakerItemMenuDialogActivity"},{"val0":"net.webmise.textspeaker.TextSpeakerAlarmReceiver","val1":"net.webmise.textspeaker.TextSpeakerAlarmService"},{"val0":"net.webmise.textspeaker.TextSpeakerAlarmReceiver","val1":"net.webmise.textspeaker.TextSpeakerSetAlarmReceiver"},{"val0":"net.webmise.textspeaker.TextSpeakerAlarmReceiver","val1":"net.webmise.textspeaker.TextSpeakerAlarmReceiver"},{"val0":"net.webmise.textspeaker.TextSpeakerAlarmReceiver","val1":"net.webmise.textspeaker.dialog.TextSpeakerItemMenuDialogActivity"},{"val0":"net.webmise.textspeaker.dialog.TextSpeakerItemMenuDialogActivity","val1":"net.webmise.textspeaker.TextSpeakerAlarmService"},{"val0":"net.webmise.textspeaker.dialog.TextSpeakerItemMenuDialogActivity","val1":"net.webmise.textspeaker.TextSpeakerSetAlarmReceiver"},{"val0":"net.webmise.textspeaker.dialog.TextSpeakerItemMenuDialogActivity","val1":"net.webmise.textspeaker.TextSpeakerAlarmReceiver"},{"val0":"net.webmise.textspeaker.dialog.TextSpeakerItemMenuDialogActivity","val1":"net.webmise.textspeaker.dialog.TextSpeakerItemMenuDialogActivity"},{"val0":"net.webmise.textspeaker.TextSpeakerAlarmService","val1":"net.webmise.textspeaker.dialog.TextSpeakerSettingDialogActivity"},{"val0":"net.webmise.textspeaker.TextSpeakerSetAlarmReceiver","val1":"net.webmise.textspeaker.dialog.TextSpeakerSettingDialogActivity"},{"val0":"net.webmise.textspeaker.TextSpeakerAlarmReceiver","val1":"net.webmise.textspeaker.dialog.TextSpeakerSettingDialogActivity"},{"val0":"net.webmise.textspeaker.dialog.TextSpeakerItemMenuDialogActivity","val1":"net.webmise.textspeaker.dialog.TextSpeakerSettingDialogActivity"},{"val0":"net.webmise.textspeaker.dialog.TextSpeakerSettingDialogActivity","val1":"net.webmise.textspeaker.TextSpeakerSplashActivity"},{"val0":"net.webmise.textspeaker.dialog.TextSpeakerSettingDialogActivity","val1":"net.webmise.textspeaker.TextSpeakerForShareActivity"},{"val0":"net.webmise.textspeaker.dialog.TextSpeakerSettingDialogActivity","val1":"net.webmise.textspeaker.TextSpeakerActivity"},{"val0":"net.webmise.textspeaker.dialog.TextSpeakerSettingDialogActivity","val1":"net.webmise.textspeaker.TextSpeakerInfoActivity"},{"val0":"net.webmise.textspeaker.dialog.TextSpeakerSettingDialogActivity","val1":"com.google.ads.AdActivity"},{"val0":"net.webmise.textspeaker.dialog.TextSpeakerSettingDialogActivity","val1":"net.webmise.textspeaker.dialog.TextSpeakerPitchRateDialogActivity"},{"val0":"net.webmise.textspeaker.dialog.TextSpeakerSettingDialogActivity","val1":"net.webmise.textspeaker.TextSpeakerStartupReceiver"},{"val0":"net.webmise.textspeaker.dialog.TextSpeakerSettingDialogActivity","val1":"net.webmise.textspeaker.dialog.TextSpeakerRegistDialogActivity"},{"val0":"net.webmise.textspeaker.dialog.TextSpeakerSettingDialogActivity","val1":"net.webmise.textspeaker.TextSpeakerAlarmService"},{"val0":"net.webmise.textspeaker.dialog.TextSpeakerSettingDialogActivity","val1":"net.webmise.textspeaker.TextSpeakerSetAlarmReceiver"},{"val0":"net.webmise.textspeaker.dialog.TextSpeakerSettingDialogActivity","val1":"net.webmise.textspeaker.TextSpeakerAlarmReceiver"},{"val0":"net.webmise.textspeaker.dialog.TextSpeakerSettingDialogActivity","val1":"net.webmise.textspeaker.dialog.TextSpeakerItemMenuDialogActivity"},{"val0":"net.webmise.textspeaker.dialog.TextSpeakerSettingDialogActivity","val1":"net.webmise.textspeaker.dialog.TextSpeakerSettingDialogActivity"}],"intentFilters":[{"val0":"net.webmise.textspeaker.TextSpeakerStartupReceiver","val1":"android.intent.action.BOOT_COMPLETED"}],"dangerAPIs":[],"taintFlows":[{"val0":"net.webmise.textspeaker.TextSpeakerAlarmService","val1":"$MyTime","val2":"net.webmise.textspeaker.TextSpeakerForShareActivity","val3":"!WebView"},{"val0":"net.webmise.textspeaker.TextSpeakerAlarmService","val1":"$MyTime","val2":"net.webmise.textspeaker.TextSpeakerForShareActivity","val3":"!INTERNET"}],"samples":[]}