{"family":"[]","activities":["com.kozmo.mathfree.Mathfree","com.millennialmedia.android.VideoPlayer","com.millennialmedia.android.MMAdViewOverlayActivity"],"services":[],"receivers":[],"iccg":[{"val0":"com.kozmo.mathfree.Mathfree","val1":"com.kozmo.mathfree.Mathfree"},{"val0":"com.kozmo.mathfree.Mathfree","val1":"com.millennialmedia.android.VideoPlayer"},{"val0":"com.millennialmedia.android.VideoPlayer","val1":"com.kozmo.mathfree.Mathfree"},{"val0":"com.millennialmedia.android.VideoPlayer","val1":"com.millennialmedia.android.VideoPlayer"},{"val0":"com.kozmo.mathfree.Mathfree","val1":"com.millennialmedia.android.MMAdViewOverlayActivity"},{"val0":"com.millennialmedia.android.VideoPlayer","val1":"com.millennialmedia.android.MMAdViewOverlayActivity"},{"val0":"com.millennialmedia.android.MMAdViewOverlayActivity","val1":"com.kozmo.mathfree.Mathfree"},{"val0":"com.millennialmedia.android.MMAdViewOverlayActivity","val1":"com.millennialmedia.android.VideoPlayer"},{"val0":"com.millennialmedia.android.MMAdViewOverlayActivity","val1":"com.millennialmedia.android.MMAdViewOverlayActivity"}],"intentFilters":[],"dangerAPIs":[],"taintFlows":[{"val0":"com.kozmo.mathfree.Mathfree","val1":"$getDeviceId","val2":"com.kozmo.mathfree.Mathfree","val3":"!WebView"},{"val0":"com.kozmo.mathfree.Mathfree","val1":"$getDeviceId","val2":"com.kozmo.mathfree.Mathfree","val3":"!FILE"},{"val0":"com.kozmo.mathfree.Mathfree","val1":"$getDeviceId","val2":"com.kozmo.mathfree.Mathfree","val3":"!INTERNET"},{"val0":"com.kozmo.mathfree.Mathfree","val1":"$SDK","val2":"com.kozmo.mathfree.Mathfree","val3":"!WebView"},{"val0":"com.kozmo.mathfree.Mathfree","val1":"$SDK","val2":"com.kozmo.mathfree.Mathfree","val3":"!FILE"},{"val0":"com.kozmo.mathfree.Mathfree","val1":"$SDK","val2":"com.kozmo.mathfree.Mathfree","val3":"!INTERNET"},{"val0":"com.kozmo.mathfree.Mathfree","val1":"$MODEL","val2":"com.kozmo.mathfree.Mathfree","val3":"!WebView"},{"val0":"com.kozmo.mathfree.Mathfree","val1":"$MODEL","val2":"com.kozmo.mathfree.Mathfree","val3":"!FILE"},{"val0":"com.kozmo.mathfree.Mathfree","val1":"$MODEL","val2":"com.kozmo.mathfree.Mathfree","val3":"!INTERNET"},{"val0":"com.kozmo.mathfree.Mathfree","val1":"$ExternalStorage","val2":"com.kozmo.mathfree.Mathfree","val3":"!WebView"},{"val0":"com.kozmo.mathfree.Mathfree","val1":"$ExternalStorage","val2":"com.kozmo.mathfree.Mathfree","val3":"!FILE"},{"val0":"com.kozmo.mathfree.Mathfree","val1":"$ExternalStorage","val2":"com.kozmo.mathfree.Mathfree","val3":"!INTERNET"},{"val0":"com.kozmo.mathfree.Mathfree","val1":"$MyTime","val2":"com.kozmo.mathfree.Mathfree","val3":"!WebView"},{"val0":"com.kozmo.mathfree.Mathfree","val1":"$MyTime","val2":"com.kozmo.mathfree.Mathfree","val3":"!FILE"},{"val0":"com.kozmo.mathfree.Mathfree","val1":"$MyTime","val2":"com.kozmo.mathfree.Mathfree","val3":"!INTERNET"},{"val0":"com.kozmo.mathfree.Mathfree","val1":"$File","val2":"com.kozmo.mathfree.Mathfree","val3":"!WebView"},{"val0":"com.kozmo.mathfree.Mathfree","val1":"$File","val2":"com.kozmo.mathfree.Mathfree","val3":"!FILE"},{"val0":"com.kozmo.mathfree.Mathfree","val1":"$File","val2":"com.kozmo.mathfree.Mathfree","val3":"!INTERNET"},{"val0":"com.kozmo.mathfree.Mathfree","val1":"$getDeviceId","val2":"com.millennialmedia.android.VideoPlayer","val3":"!INTERNET"},{"val0":"com.kozmo.mathfree.Mathfree","val1":"$SDK","val2":"com.millennialmedia.android.VideoPlayer","val3":"!INTERNET"},{"val0":"com.kozmo.mathfree.Mathfree","val1":"$MODEL","val2":"com.millennialmedia.android.VideoPlayer","val3":"!INTERNET"},{"val0":"com.kozmo.mathfree.Mathfree","val1":"$ExternalStorage","val2":"com.millennialmedia.android.VideoPlayer","val3":"!INTERNET"},{"val0":"com.kozmo.mathfree.Mathfree","val1":"$MyTime","val2":"com.millennialmedia.android.VideoPlayer","val3":"!INTERNET"},{"val0":"com.kozmo.mathfree.Mathfree","val1":"$File","val2":"com.millennialmedia.android.VideoPlayer","val3":"!INTERNET"},{"val0":"com.kozmo.mathfree.Mathfree","val1":"$getDeviceId","val2":"com.millennialmedia.android.MMAdViewOverlayActivity","val3":"!WebView"},{"val0":"com.kozmo.mathfree.Mathfree","val1":"$getDeviceId","val2":"com.millennialmedia.android.MMAdViewOverlayActivity","val3":"!INTERNET"},{"val0":"com.kozmo.mathfree.Mathfree","val1":"$SDK","val2":"com.millennialmedia.android.MMAdViewOverlayActivity","val3":"!WebView"},{"val0":"com.kozmo.mathfree.Mathfree","val1":"$SDK","val2":"com.millennialmedia.android.MMAdViewOverlayActivity","val3":"!INTERNET"},{"val0":"com.kozmo.mathfree.Mathfree","val1":"$MODEL","val2":"com.millennialmedia.android.MMAdViewOverlayActivity","val3":"!WebView"},{"val0":"com.kozmo.mathfree.Mathfree","val1":"$MODEL","val2":"com.millennialmedia.android.MMAdViewOverlayActivity","val3":"!INTERNET"},{"val0":"com.kozmo.mathfree.Mathfree","val1":"$ExternalStorage","val2":"com.millennialmedia.android.MMAdViewOverlayActivity","val3":"!WebView"},{"val0":"com.kozmo.mathfree.Mathfree","val1":"$ExternalStorage","val2":"com.millennialmedia.android.MMAdViewOverlayActivity","val3":"!INTERNET"},{"val0":"com.kozmo.mathfree.Mathfree","val1":"$MyTime","val2":"com.millennialmedia.android.MMAdViewOverlayActivity","val3":"!WebView"},{"val0":"com.kozmo.mathfree.Mathfree","val1":"$MyTime","val2":"com.millennialmedia.android.MMAdViewOverlayActivity","val3":"!INTERNET"},{"val0":"com.kozmo.mathfree.Mathfree","val1":"$File","val2":"com.millennialmedia.android.MMAdViewOverlayActivity","val3":"!WebView"},{"val0":"com.kozmo.mathfree.Mathfree","val1":"$File","val2":"com.millennialmedia.android.MMAdViewOverlayActivity","val3":"!INTERNET"},{"val0":"com.millennialmedia.android.VideoPlayer","val1":"$ExternalStorage","val2":"com.kozmo.mathfree.Mathfree","val3":"!WebView"},{"val0":"com.millennialmedia.android.VideoPlayer","val1":"$ExternalStorage","val2":"com.kozmo.mathfree.Mathfree","val3":"!FILE"},{"val0":"com.millennialmedia.android.VideoPlayer","val1":"$ExternalStorage","val2":"com.kozmo.mathfree.Mathfree","val3":"!INTERNET"},{"val0":"com.millennialmedia.android.VideoPlayer","val1":"$File","val2":"com.kozmo.mathfree.Mathfree","val3":"!WebView"},{"val0":"com.millennialmedia.android.VideoPlayer","val1":"$File","val2":"com.kozmo.mathfree.Mathfree","val3":"!FILE"},{"val0":"com.millennialmedia.android.VideoPlayer","val1":"$File","val2":"com.kozmo.mathfree.Mathfree","val3":"!INTERNET"},{"val0":"com.millennialmedia.android.VideoPlayer","val1":"$ExternalStorage","val2":"com.millennialmedia.android.VideoPlayer","val3":"!INTERNET"},{"val0":"com.millennialmedia.android.VideoPlayer","val1":"$File","val2":"com.millennialmedia.android.VideoPlayer","val3":"!INTERNET"},{"val0":"com.millennialmedia.android.VideoPlayer","val1":"$ExternalStorage","val2":"com.millennialmedia.android.MMAdViewOverlayActivity","val3":"!WebView"},{"val0":"com.millennialmedia.android.VideoPlayer","val1":"$ExternalStorage","val2":"com.millennialmedia.android.MMAdViewOverlayActivity","val3":"!INTERNET"},{"val0":"com.millennialmedia.android.VideoPlayer","val1":"$File","val2":"com.millennialmedia.android.MMAdViewOverlayActivity","val3":"!WebView"},{"val0":"com.millennialmedia.android.VideoPlayer","val1":"$File","val2":"com.millennialmedia.android.MMAdViewOverlayActivity","val3":"!INTERNET"}],"samples":[]}