{"family":"[]","activities":["com.google.ads.AdActivity","kr.nalae.emoticon.ScrIntro","kr.nalae.emoticon.eMOTiConMain"],"services":[],"receivers":[],"iccg":[{"val0":"kr.nalae.emoticon.ScrIntro","val1":"com.google.ads.AdActivity"},{"val0":"kr.nalae.emoticon.ScrIntro","val1":"kr.nalae.emoticon.ScrIntro"},{"val0":"kr.nalae.emoticon.ScrIntro","val1":"kr.nalae.emoticon.eMOTiConMain"},{"val0":"kr.nalae.emoticon.eMOTiConMain","val1":"com.google.ads.AdActivity"},{"val0":"kr.nalae.emoticon.eMOTiConMain","val1":"kr.nalae.emoticon.ScrIntro"},{"val0":"kr.nalae.emoticon.eMOTiConMain","val1":"kr.nalae.emoticon.eMOTiConMain"}],"intentFilters":[],"dangerAPIs":[],"taintFlows":[],"samples":[]}