{"family":"[]","activities":["com.mobilegame.sokoban.activitys1.ScoresList","com.mobilegame.sokoban.activitys1.MenuActivity","com.mobilegame.sokoban.activitys1.GameActivity","com.mobilegame.sokoban.activitys1.OverActivity","com.mobilegame.sokoban.activitys1.OptionsActivity"],"services":[],"receivers":[],"iccg":[{"val0":"com.mobilegame.sokoban.activitys1.MenuActivity","val1":"com.mobilegame.sokoban.activitys1.ScoresList"},{"val0":"com.mobilegame.sokoban.activitys1.MenuActivity","val1":"com.mobilegame.sokoban.activitys1.MenuActivity"},{"val0":"com.mobilegame.sokoban.activitys1.MenuActivity","val1":"com.mobilegame.sokoban.activitys1.GameActivity"},{"val0":"com.mobilegame.sokoban.activitys1.MenuActivity","val1":"com.mobilegame.sokoban.activitys1.OverActivity"},{"val0":"com.mobilegame.sokoban.activitys1.MenuActivity","val1":"com.mobilegame.sokoban.activitys1.OptionsActivity"},{"val0":"com.mobilegame.sokoban.activitys1.GameActivity","val1":"com.mobilegame.sokoban.activitys1.ScoresList"},{"val0":"com.mobilegame.sokoban.activitys1.GameActivity","val1":"com.mobilegame.sokoban.activitys1.MenuActivity"},{"val0":"com.mobilegame.sokoban.activitys1.GameActivity","val1":"com.mobilegame.sokoban.activitys1.GameActivity"},{"val0":"com.mobilegame.sokoban.activitys1.GameActivity","val1":"com.mobilegame.sokoban.activitys1.OverActivity"},{"val0":"com.mobilegame.sokoban.activitys1.OverActivity","val1":"com.mobilegame.sokoban.activitys1.ScoresList"},{"val0":"com.mobilegame.sokoban.activitys1.OverActivity","val1":"com.mobilegame.sokoban.activitys1.MenuActivity"},{"val0":"com.mobilegame.sokoban.activitys1.OverActivity","val1":"com.mobilegame.sokoban.activitys1.GameActivity"},{"val0":"com.mobilegame.sokoban.activitys1.OverActivity","val1":"com.mobilegame.sokoban.activitys1.OverActivity"},{"val0":"com.mobilegame.sokoban.activitys1.GameActivity","val1":"com.mobilegame.sokoban.activitys1.OptionsActivity"},{"val0":"com.mobilegame.sokoban.activitys1.OverActivity","val1":"com.mobilegame.sokoban.activitys1.OptionsActivity"}],"intentFilters":[],"dangerAPIs":[],"taintFlows":[{"val0":"com.mobilegame.sokoban.activitys1.GameActivity","val1":"$getDeviceId","val2":"com.mobilegame.sokoban.activitys1.GameActivity","val3":"!INTERNET"},{"val0":"com.mobilegame.sokoban.activitys1.GameActivity","val1":"$getSimSerialNumber","val2":"com.mobilegame.sokoban.activitys1.GameActivity","val3":"!INTERNET"},{"val0":"com.mobilegame.sokoban.activitys1.GameActivity","val1":"$getLine1Number","val2":"com.mobilegame.sokoban.activitys1.GameActivity","val3":"!INTERNET"},{"val0":"com.mobilegame.sokoban.activitys1.GameActivity","val1":"$MODEL","val2":"com.mobilegame.sokoban.activitys1.GameActivity","val3":"!INTERNET"},{"val0":"com.mobilegame.sokoban.activitys1.GameActivity","val1":"$MyTime","val2":"com.mobilegame.sokoban.activitys1.GameActivity","val3":"!INTERNET"},{"val0":"com.mobilegame.sokoban.activitys1.GameActivity","val1":"$MyDate","val2":"com.mobilegame.sokoban.activitys1.GameActivity","val3":"!INTERNET"}],"samples":[]}