{"family":"[]","activities":["com.google.ads.AdActivity","com.advan.HHCDevilMayCry1.HHCDevilMayCry1","com.advan.HHCDevilMayCry1.fullScreenAct"],"services":[],"receivers":[],"iccg":[{"val0":"com.advan.HHCDevilMayCry1.HHCDevilMayCry1","val1":"com.google.ads.AdActivity"},{"val0":"com.advan.HHCDevilMayCry1.HHCDevilMayCry1","val1":"com.advan.HHCDevilMayCry1.HHCDevilMayCry1"},{"val0":"com.advan.HHCDevilMayCry1.HHCDevilMayCry1","val1":"com.advan.HHCDevilMayCry1.fullScreenAct"}],"intentFilters":[],"dangerAPIs":[],"taintFlows":[],"samples":[]}