{"family":"[]","activities":["net.soukyu.widget.battery.maid.WidgetBatteryActivity","net.soukyu.widget.battery.maid.WallpaperFirstActivity"],"services":["net.soukyu.widget.battery.maid.WidgetService","net.soukyu.widget.battery.maid.WidgetNotifyService","net.soukyu.widget.battery.maid.WidgetActivityService"],"receivers":["net.soukyu.widget.battery.maid.Widget"],"iccg":[{"val0":"net.soukyu.widget.battery.maid.WidgetService","val1":"net.soukyu.widget.battery.maid.WidgetService"},{"val0":"net.soukyu.widget.battery.maid.WidgetService","val1":"net.soukyu.widget.battery.maid.WidgetNotifyService"},{"val0":"net.soukyu.widget.battery.maid.Widget","val1":"net.soukyu.widget.battery.maid.WidgetService"},{"val0":"net.soukyu.widget.battery.maid.Widget","val1":"net.soukyu.widget.battery.maid.WidgetNotifyService"}],"intentFilters":[],"dangerAPIs":[],"taintFlows":[]}